ctx_gen/__init__.py
ctx_gen/cli.py
ctx_gen-0.3.0.dist-info/METADATA
ctx_gen-0.3.0.dist-info/WHEEL
ctx_gen-0.3.0.dist-info/entry_points.txt
ctx_gen-0.3.0.dist-info/licenses/LICENSE
ctx_gen-0.3.0.dist-info/RECORD
