Metadata-Version: 2.4
Name: ctx-gen
Version: 0.3.0
Summary: An intelligent code context generator that converts project structure and file contents into LLM-friendly formats.
Project-URL: Homepage, https://github.com/foxmcp/ctx-gen
Project-URL: Issues, https://github.com/foxmcp/ctx-gen/issues
Author-email: foxmcp <ctx-gen@foxmcp.com>
License: MIT
License-File: LICENSE
Keywords: ai,artificial intelligence,chatgpt,claude,cli,code analysis,code context,code generation,context generator,copilot,dev productivity,developer tools,file contents,gpt,large language model,llm,lmarena.ai,markdown,project structure,prompt,prompt engineering,text formatting
Classifier: Development Status :: 4 - Beta
Classifier: Environment :: Console
Classifier: Intended Audience :: Developers
Classifier: License :: OSI Approved :: MIT License
Classifier: Operating System :: OS Independent
Classifier: Programming Language :: Python :: 3
Classifier: Programming Language :: Python :: 3.8
Classifier: Programming Language :: Python :: 3.9
Classifier: Programming Language :: Python :: 3.10
Classifier: Programming Language :: Python :: 3.11
Classifier: Programming Language :: Python :: 3.12
Classifier: Topic :: Scientific/Engineering :: Artificial Intelligence
Classifier: Topic :: Software Development :: Code Generators
Classifier: Topic :: Software Development :: Libraries :: Python Modules
Classifier: Topic :: Text Processing
Classifier: Topic :: Utilities
Requires-Python: >=3.8
Requires-Dist: pathspec>=0.12.1
Requires-Dist: pyperclip>=1.9.0
Requires-Dist: rich>=13.0.0
Requires-Dist: tiktoken>=0.5.0
Requires-Dist: typer>=0.9.0
Provides-Extra: dev
Requires-Dist: black>=23.0.0; extra == 'dev'
Requires-Dist: mypy>=1.0.0; extra == 'dev'
Requires-Dist: pre-commit>=3.0.0; extra == 'dev'
Requires-Dist: pytest-cov>=4.0.0; extra == 'dev'
Requires-Dist: pytest-mock>=3.0.0; extra == 'dev'
Requires-Dist: pytest>=7.0.0; extra == 'dev'
Requires-Dist: ruff>=0.1.0; extra == 'dev'
Requires-Dist: types-setuptools; extra == 'dev'
